smart_search/__init__.py
smart_search-0.0.5.dist-info/LICENSE
smart_search-0.0.5.dist-info/METADATA
smart_search-0.0.5.dist-info/WHEEL
smart_search-0.0.5.dist-info/top_level.txt
smart_search-0.0.5.dist-info/RECORD
