Metadata-Version: 2.1
Name: smart-search
Version: 0.0.5
Summary: A search algorithm for efficient searching in PDFs
Home-page: https://github.com/ItsSiddharth/context_search
Author: Siddharth Menon
Author-email: siddharth.menon1@gmail.com
License: UNKNOWN
Platform: UNKNOWN
Classifier: Programming Language :: Python :: 3
Classifier: License :: OSI Approved :: MIT License
Classifier: Operating System :: OS Independent
Requires-Python: >=3.6
